{
  "playlists": [
    {
      "id": "PLordIU6tK3nVRzSDaRITfSwBwy7N4JzBf",
      "name": "Headless Creator",
      "folder": "headless-creator",
      "enabled": true
    },
    {
      "id": "PLcoeeDyxakhUdkUvZm8qld1YuInOKOLqT",
      "name": "Alive And Kicking",
      "folder": "alive-and-kicking",
      "enabled": true
    },
    {
      "id": "",
      "name": "Contentstack",
      "folder": "contentstack",
      "enabled": true
    },
    {
      "id": "",
      "name": "Hygraph",
      "folder": "hygraph",
      "enabled": true
    }
  ]
}